astroquery/CITATION
astroquery/__init__.py
astroquery/_astropy_init.py
astroquery/conftest.py
astroquery/exceptions.py
astroquery/logger.py
astroquery/query.py
astroquery/setup_package.py
astroquery/version.py
astroquery/alfalfa/__init__.py
astroquery/alfalfa/core.py
astroquery/alfalfa/tests/__init__.py
astroquery/alfalfa/tests/setup_package.py
astroquery/alfalfa/tests/test_alfalfa.py
astroquery/alfalfa/tests/data/alfalfa_cat_small.txt
astroquery/alfalfa/tests/data/alfalfa_sp.fits
astroquery/alma/__init__.py
astroquery/alma/core.py
astroquery/alma/setup_package.py
astroquery/alma/tapsql.py
astroquery/alma/utils.py
astroquery/alma/data/cycle0_delivery_asdm_mapping.txt
astroquery/alma/tests/__init__.py
astroquery/alma/tests/setup_package.py
astroquery/alma/tests/test_alma.py
astroquery/alma/tests/test_alma_auth.py
astroquery/alma/tests/test_alma_remote.py
astroquery/alma/tests/test_alma_utils.py
astroquery/alma/tests/data/alma-datalink-recurse-aux.xml
astroquery/alma/tests/data/alma-datalink-recurse-this.xml
astroquery/alma/tests/data/alma-datalink.xml
astroquery/alma/tests/data/alma-empty.txt
astroquery/alma/tests/data/alma-onerow.txt
astroquery/alma/tests/data/alma-shapes.xml
astroquery/astrometry_net/__init__.py
astroquery/astrometry_net/core.py
astroquery/astrometry_net/tests/__init__.py
astroquery/astrometry_net/tests/setup_package.py
astroquery/astrometry_net/tests/test_astrometry_net.py
astroquery/astrometry_net/tests/test_astrometry_net_remote.py
astroquery/astrometry_net/tests/data/test-source-list.fit
astroquery/astrometry_net/tests/data/test-wcs-sol.fit
astroquery/astrometry_net/tests/data/thumbnail-image.fit.gz
astroquery/astrometry_net/tests/data/wcs-sol-from-source-list-index-5200.fit
astroquery/astrometry_net/tests/data/wcs-sol-from-thumbnail-image-index-5200.fit
astroquery/atomic/__init__.py
astroquery/atomic/core.py
astroquery/atomic/setup_package.py
astroquery/atomic/utils.py
astroquery/atomic/tests/__init__.py
astroquery/atomic/tests/test_atomic.py
astroquery-0.4.9.dist-info/LICENSE.rst
astroquery-0.4.9.dist-info/METADATA
astroquery-0.4.9.dist-info/WHEEL
astroquery-0.4.9.dist-info/top_level.txt
astroquery-0.4.9.dist-info/RECORD
